relatio/__init__.py
relatio/datasets.py
relatio/dependency_parsing.py
relatio/embeddings.py
relatio/graphs.py
relatio/logging.py
relatio/narrative_models.py
relatio/preprocessing.py
relatio/semantic_role_labeling.py
relatio/supported_models.py
relatio/utils.py
relatio/verbs.py
relatio-0.3.0.dist-info/LICENSE
relatio-0.3.0.dist-info/METADATA
relatio-0.3.0.dist-info/WHEEL
relatio-0.3.0.dist-info/top_level.txt
relatio-0.3.0.dist-info/RECORD
