Metadata-Version: 2.1
Name: relatio
Version: 0.3.0
Summary: A Python package to extract narrative statements from text
Home-page: https://github.com/relatio-nlp/relatio
Author: Andrei V. Plamada
Author-email: plamadaa@ethz.ch
License: MIT License
Keywords: NLP,narrative
Classifier: License :: OSI Approved :: MIT License
Classifier: Programming Language :: Python :: 3
Classifier: Programming Language :: Python :: 3.7
Classifier: Programming Language :: Python :: 3.8
Requires-Python: >=3.7
License-File: LICENSE
Requires-Dist: pandas (>=1)
Requires-Dist: nltk (>=3)
Requires-Dist: spacy (>=3.3.2)
Requires-Dist: gensim (>=3)
Requires-Dist: scikit-learn (>=0.22)
Requires-Dist: allennlp-models (>=2.3)
Requires-Dist: networkx (>=2.5)
Requires-Dist: pyvis (>=0.1.9)
Requires-Dist: matplotlib (>=3)
Requires-Dist: requests (>=2)
Requires-Dist: umap-learn (>=0.5.3)
Requires-Dist: joblib (>=1.1.0)
Requires-Dist: hdbscan (>=0.8.28)
Requires-Dist: kneed (>=0.8.2)
Requires-Dist: sentence-transformers (>=2.2.2)
